cv2imshow/README.MD
cv2imshow/__init__.py
cv2imshow/cv2imshow.py
cv2imshow/cv2imshowsafe.py
cv2imshow/requirements.txt
cv2imshow/thirdparty.json
cv2imshow-0.10.dist-info/LICENSE.rst
cv2imshow-0.10.dist-info/METADATA
cv2imshow-0.10.dist-info/WHEEL
cv2imshow-0.10.dist-info/top_level.txt
cv2imshow-0.10.dist-info/RECORD
