Metadata-Version: 2.1
Name: cv2imshow
Version: 0.10
Summary: cv2.imshow without freezing - Windows only
Home-page: https://github.com/hansalemaos/cv2imshow
Author: Johannes Fischer
Author-email: aulasparticularesdealemaosp@gmail.com
License: MIT
Keywords: cv2,imshow
Classifier: Development Status :: 4 - Beta
Classifier: Programming Language :: Python :: 3 :: Only
Classifier: Programming Language :: Python :: 3.10
Classifier: Topic :: Software Development :: Libraries :: Python Modules
Classifier: Topic :: Utilities
License-File: LICENSE.rst
Requires-Dist: hackyargparser
Requires-Dist: keyboard
Requires-Dist: kthread-sleep
Requires-Dist: numpy
Requires-Dist: opencv-python
Requires-Dist: subprocess-alive
Requires-Dist: subprocess-multipipe
Requires-Dist: varpickler
